getgse/__init__.py
getgse/getgse.py
getgse-0.1.0.10.dist-info/LICENSE
getgse-0.1.0.10.dist-info/METADATA
getgse-0.1.0.10.dist-info/WHEEL
getgse-0.1.0.10.dist-info/dependency_links.txt
getgse-0.1.0.10.dist-info/entry_points.txt
getgse-0.1.0.10.dist-info/top_level.txt
getgse-0.1.0.10.dist-info/RECORD
