Metadata-Version: 2.1
Name: getgse
Version: 0.1.0.10
Summary: UNKNOWN
Home-page: https://github.com/Alopaxalgo/getGSE
Author: William Jeong
Author-email: wjd5480@gmail.com
License: MIT
Keywords: getgse
Platform: UNKNOWN
Classifier: License :: OSI Approved :: MIT License
Classifier: Programming Language :: Python :: 3.7
Requires-Python: >=3.7
Requires-Dist: pysradb (>=1.4.2)
Requires-Dist: docker
Requires-Dist: wget
